{"cameraMode":{"drawMode":0,"name":"Shaded","section":"Shading Mode"},"sceneLighting":false,"audioPlay":false,"sceneViewState":{"m_AlwaysRefresh":false,"showFog":true,"showSkybox":false,"showFlares":true,"showImageEffects":true,"showParticleSystems":true,"showVisualEffectGraphs":true,"m_FxEnabled":true},"in2DMode":false,"pivot":{"x":1.4250309467315674,"y":1.9916791915893555,"z":-8.485352516174317},"rotation":{"x":-0.14997127652168275,"y":-0.659478485584259,"z":0.13665640354156495,"w":-0.7238451242446899},"size":1.8484712839126588,"orthographic":false}